README.md
setup.py
geo_cache_client/__init__.py
geo_cache_client/cache_client.py
geo_cache_client.egg-info/PKG-INFO
geo_cache_client.egg-info/SOURCES.txt
geo_cache_client.egg-info/dependency_links.txt
geo_cache_client.egg-info/top_level.txt