Metadata-Version: 2.1
Name: geo-cache-client
Version: 0.1.2
Summary: A geo distributed cache
Home-page: https://github.com/timbo-rafa/geo-cache
Author: Rafael
Author-email: timbo.rafa@gmail.com
License: UNKNOWN
Platform: UNKNOWN
Classifier: Programming Language :: Python :: 3
Classifier: License :: OSI Approved :: MIT License
Classifier: Operating System :: OS Independent
Requires-Python: >=3.6
